{
    "head": {},
    "def": [
        {
            "text": "penned",
            "pos": "participle",
            "ts": "pend",
            "tr": [
                {
                    "text": "написанный",
                    "pos": "participle",
                    "syn": [
                        {
                            "text": "сочиненный",
                            "pos": "participle"
                        }
                    ],
                    "mean": [
                        {
                            "text": "written"
                        },
                        {
                            "text": "composed"
                        }
                    ]
                }
            ]
        }
    ]
}