{
    "head": {},
    "def": [
        {
            "text": "бразильский",
            "pos": "adjective",
            "tr": [
                {
                    "text": "brésilien",
                    "pos": "adjective",
                    "ex": [
                        {
                            "text": "бразильский футболист",
                            "tr": [
                                {
                                    "text": "footballeur brésilien"
                                }
                            ]
                        }
                    ]
                }
            ]
        }
    ]
}