{
    "head": {},
    "def": [
        {
            "text": "разгон",
            "pos": "noun",
            "gen": "м",
            "anm": "неодуш",
            "tr": [
                {
                    "text": "accélération",
                    "pos": "noun",
                    "gen": "f",
                    "syn": [
                        {
                            "text": "dispersion",
                            "pos": "noun",
                            "gen": "f"
                        }
                    ],
                    "mean": [
                        {
                            "text": "ускорение"
                        },
                        {
                            "text": "рассеивание"
                        }
                    ],
                    "ex": [
                        {
                            "text": "быстрый разгон",
                            "tr": [
                                {
                                    "text": "accélération rapide"
                                }
                            ]
                        }
                    ]
                },
                {
                    "text": "démarrage",
                    "pos": "noun",
                    "gen": "m",
                    "mean": [
                        {
                            "text": "пуск"
                        }
                    ],
                    "ex": [
                        {
                            "text": "время разгона",
                            "tr": [
                                {
                                    "text": "temps de démarrage"
                                }
                            ]
                        }
                    ]
                },
                {
                    "text": "élan",
                    "pos": "noun",
                    "gen": "m",
                    "mean": [
                        {
                            "text": "разбег"
                        }
                    ]
                },
                {
                    "text": "emballement",
                    "pos": "noun",
                    "gen": "m"
                },
                {
                    "text": "reprise",
                    "pos": "noun",
                    "gen": "f",
                    "mean": [
                        {
                            "text": "подхват"
                        }
                    ]
                },
                {
                    "text": "recul",
                    "pos": "noun",
                    "gen": "m",
                    "mean": [
                        {
                            "text": "отскок"
                        }
                    ]
                }
            ]
        }
    ]
}