{
    "head": {},
    "def": [
        {
            "text": "распорядок",
            "pos": "noun",
            "gen": "м",
            "anm": "неодуш",
            "tr": [
                {
                    "text": "horaire",
                    "pos": "noun",
                    "gen": "m",
                    "mean": [
                        {
                            "text": "график"
                        }
                    ],
                    "ex": [
                        {
                            "text": "распорядок дня",
                            "tr": [
                                {
                                    "text": "horaire quotidien"
                                }
                            ]
                        }
                    ]
                },
                {
                    "text": "ordre",
                    "pos": "noun",
                    "gen": "m",
                    "syn": [
                        {
                            "text": "régime",
                            "pos": "noun",
                            "gen": "m"
                        },
                        {
                            "text": "ordonnance",
                            "pos": "noun",
                            "gen": "f"
                        }
                    ],
                    "mean": [
                        {
                            "text": "порядок"
                        },
                        {
                            "text": "приказ"
                        }
                    ]
                }
            ]
        }
    ]
}