{
    "head": {},
    "def": [
        {
            "text": "скоба",
            "pos": "noun",
            "gen": "ж",
            "anm": "неодуш",
            "tr": [
                {
                    "text": "agrafe",
                    "pos": "noun",
                    "gen": "f",
                    "syn": [
                        {
                            "text": "étrier",
                            "pos": "noun",
                            "gen": "m"
                        },
                        {
                            "text": "patte",
                            "pos": "noun",
                            "gen": "f"
                        },
                        {
                            "text": "bride",
                            "pos": "noun",
                            "gen": "f"
                        },
                        {
                            "text": "pontet",
                            "pos": "noun",
                            "gen": "m"
                        },
                        {
                            "text": "crochet",
                            "pos": "noun",
                            "gen": "m"
                        },
                        {
                            "text": "pince",
                            "pos": "noun",
                            "gen": "f"
                        },
                        {
                            "text": "chape",
                            "pos": "noun",
                            "gen": "f"
                        },
                        {
                            "text": "attache",
                            "pos": "noun",
                            "gen": "f"
                        },
                        {
                            "text": "poignée",
                            "pos": "noun",
                            "gen": "f"
                        },
                        {
                            "text": "crampon",
                            "pos": "noun",
                            "gen": "m"
                        },
                        {
                            "text": "décrottoir",
                            "pos": "noun",
                            "gen": "m"
                        },
                        {
                            "text": "collier",
                            "pos": "noun",
                            "gen": "m"
                        },
                        {
                            "text": "clip",
                            "pos": "noun",
                            "gen": "m"
                        },
                        {
                            "text": "fourche",
                            "pos": "noun",
                            "gen": "f"
                        }
                    ],
                    "mean": [
                        {
                            "text": "зажим"
                        },
                        {
                            "text": "хомут"
                        },
                        {
                            "text": "крюк"
                        },
                        {
                            "text": "кронштейн"
                        },
                        {
                            "text": "рукоятка"
                        },
                        {
                            "text": "скребок"
                        },
                        {
                            "text": "вилка"
                        }
                    ]
                },
                {
                    "text": "crampillon",
                    "pos": "noun",
                    "gen": "m",
                    "syn": [
                        {
                            "text": "manille",
                            "pos": "noun",
                            "gen": "f"
                        }
                    ],
                    "mean": [
                        {
                            "text": "серьга"
                        }
                    ]
                },
                {
                    "text": "bride de fixation",
                    "pos": "noun"
                },
                {
                    "text": "main",
                    "pos": "noun",
                    "gen": "f",
                    "mean": [
                        {
                            "text": "крюк"
                        }
                    ]
                },
                {
                    "text": "portant",
                    "pos": "noun",
                    "gen": "m",
                    "mean": [
                        {
                            "text": "ручка"
                        }
                    ]
                }
            ]
        }
    ]
}