{
    "head": {},
    "def": [
        {
            "text": "слесарь",
            "pos": "noun",
            "gen": "м",
            "anm": "одуш",
            "tr": [
                {
                    "text": "serrurier",
                    "pos": "noun",
                    "gen": "m",
                    "syn": [
                        {
                            "text": "mécanicien",
                            "pos": "noun",
                            "gen": "m"
                        },
                        {
                            "text": "ajusteur",
                            "pos": "noun",
                            "gen": "m"
                        }
                    ],
                    "mean": [
                        {
                            "text": "механик"
                        },
                        {
                            "text": "наладчик"
                        }
                    ]
                },
                {
                    "text": "monteur",
                    "pos": "noun",
                    "gen": "m",
                    "mean": [
                        {
                            "text": "монтажник"
                        }
                    ]
                }
            ]
        }
    ]
}