[
    {
        "word_id":481101,
        "word":"впустить",
        "ref_id":1,
        "setting_id":2,
        "simlar_words":[
            "просить",
            "простить",
            "светить",
            "платить",
            "льстить",
            "опустить",
            "запускать",
            "пугающий",
            "приходить",
            "звонить",
            "говорить",
            "портить",
            "крутить",
            "нестись",
            "впускать",
            "упустить",
            "выпускать",
            "моросящий",
            "спастись",
            "жидкость",
            "описать",
            "помнить"
        ]
    },
    {
        "word_id":481114,
        "word":"арканах",
        "ref_id":1,
        "setting_id":1,
        "simlar_words":[
            "аромат",
            "сарказм",
            "ударять",
            "куртка",
            "авокадо",
            "органы",
            "дракон",
            "лацкан",
            "ливень",
            "питание",
            "лёгкий",
            "барабан",
            "карате",
            "растущий",
            "запекать",
            "маргарин",
            "каркас",
            "вариант",
            "балкон",
            "карман",
            "прокат"
        ]
    },
    {
        "word_id":481114,
        "word":"арканы",
        "ref_id":1,
        "setting_id":2,
        "simlar_words":[
            "арена",
            "сарказм",
            "баран",
            "матка",
            "карты",
            "органы",
            "туман",
            "лацкан",
            "банка",
            "бекон",
            "маска",
            "варан",
            "тарелка",
            "обман",
            "роман",
            "диван",
            "марка",
            "каркас",
            "лапша",
            "пряжка",
            "карман"
        ]
    },
    {
        "word_id":481114,
        "word":"петли,аркан",
        "ref_id":1,
        "setting_id":4,
        "simlar_words":[
            "переваривать",
            "моргать",
            "пятнадцать",
            "предполагать",
            "прекращать",
            "палки",
            "преследовал",
            "передавать",
            "тринадцать",
            "пережаренный",
            "потливость",
            "пересекать",
            "полировать",
            "сверкающий",
            "четырнадцать",
            "привлекать",
            "перезаряжать",
            "резать",
            "принуждать",
            "предлагать"
        ]
    },
    {
        "word_id":481115,
        "word":"только",
        "ref_id":1,
        "setting_id":4,
        "simlar_words":[
            "слова",
            "опека",
            "полет",
            "кратко",
            "письмо",
            "почка",
            "полосы",
            "яблоко",
            "может",
            "точный",
            "голубь",
            "около",
            "больно",
            "тощий",
            "тогда",
            "холст",
            "крепко",
            "должное",
            "польза",
            "твёрдо",
            "белье"
        ]
    },
    {
        "word_id":481120,
        "word":"джеки",
        "ref_id":1,
        "setting_id":1,
        "simlar_words":[
            "опека",
            "сюжет",
            "река",
            "очки",
            "дефис",
            "дело",
            "щека",
            "ожог",
            "девиз",
            "редко",
            "дела",
            "доска",
            "бить",
            "джинн",
            "жених",
            "дымка",
            "дверь",
            "жена",
            "лжец",
            "широко",
            "резкий"
        ]
    },
    {
        "word_id":481143,
        "word":"энджи",
        "ref_id":1,
        "setting_id":2,
        "simlar_words":[
            "ниже",
            "днем",
            "свежий",
            "вести",
            "медь",
            "один",
            "вниз",
            "лоджия",
            "удав",
            "енот",
            "этаж",
            "нужда",
            "нужно",
            "индюк",
            "нрав",
            "джинн",
            "лужа",
            "знал",
            "ножи",
            "ноги"
        ]
    },
    {
        "word_id":481143,
        "word":"",
        "ref_id":1,
        "setting_id":3,
        "simlar_words":[
            "почти",
            "пение",
            "какой",
            "полосы",
            "яблоко",
            "любой",
            "бремя",
            "сталь",
            "плита",
            "писать",
            "вытащил",
            "страх",
            "кусать",
            "вялый",
            "тающий",
            "вместо",
            "шприц",
            "топить",
            "мясник",
            "выбрал",
            "ремень",
            "фокус"
        ]
    },
    {
        "word_id":481157,
        "word":"фэрвью",
        "ref_id":1,
        "setting_id":3,
        "simlar_words":[
            "любить",
            "стоит",
            "красть",
            "платить",
            "когти",
            "рвать",
            "выучил",
            "гасить",
            "ставит",
            "уволен",
            "брить",
            "брать",
            "решил",
            "расти",
            "покой",
            "давать",
            "носить",
            "заявил",
            "украл",
            "сдаёт",
            "ходить",
            "петли"
        ]
    },
    {
        "word_id":481187,
        "word":"вычеркивать",
        "ref_id":1,
        "setting_id":1,
        "simlar_words":[
            "выращивать",
            "вытаскивать",
            "выигрывает",
            "вспоминать",
            "обертывать",
            "разбрасывать",
            "встраивать",
            "отскакивать",
            "подчёркивать",
            "напоминать",
            "действовать",
            "выслеживать",
            "выскакивать",
            "удерживать",
            "выдумывать",
            "сдерживать",
            "выговаривать",
            "увеличивать",
            "выигрывать",
            "поддерживать"
        ]
    },
    {
        "word_id":481190,
        "word":"фанера",
        "ref_id":1,
        "setting_id":1,
        "simlar_words":[
            "сатира",
            "сфера",
            "пещера",
            "панда",
            "ветер",
            "канва",
            "банка",
            "заноза",
            "пантера",
            "факел",
            "монета",
            "ванна",
            "надежды",
            "банда",
            "канава",
            "хакер",
            "защита",
            "замена",
            "лагерь",
            "панама",
            "монеты",
            "фужер"
        ]
    },
    {
        "word_id":481211,
        "word":"шашлык",
        "ref_id":1,
        "setting_id":1,
        "simlar_words":[
            "ярлык",
            "палки",
            "каждый",
            "шаблон",
            "школа",
            "голый",
            "карлик",
            "прошлый",
            "разный",
            "шакал",
            "малыш",
            "целый",
            "каблуки",
            "жулик",
            "каблук",
            "палка",
            "чулок",
            "навыки",
            "батик",
            "халва"
        ]
    },
    {
        "word_id":481219,
        "word":"свитере",
        "ref_id":1,
        "setting_id":1,
        "simlar_words":[
            "акушер",
            "статья",
            "зритель",
            "тренер",
            "семинар",
            "слизерин",
            "свинья",
            "скелет",
            "ловить",
            "цветок",
            "считать",
            "эпитет",
            "святыня",
            "поиски",
            "пример",
            "приятель",
            "стимул",
            "потеря",
            "триллер",
            "скорее",
            "выборы"
        ]
    },
    {
        "word_id":481282,
        "word":"бороться",
        "ref_id":1,
        "setting_id":2,
        "simlar_words":[
            "удалось",
            "сдаваться",
            "годиться",
            "роговица",
            "остался",
            "покоиться",
            "бояться",
            "поднялся",
            "унижаться",
            "нарочно",
            "молиться",
            "длиться",
            "стараться",
            "казаться",
            "уселась",
            "порхать",
            "мчаться",
            "броситься",
            "бросаться",
            "драться"
        ]
    },
    {
        "word_id":481304,
        "word":"свободолюбивые",
        "ref_id":1,
        "setting_id":1,
        "simlar_words":[
            "должен",
            "колокол",
            "броги",
            "вежливо",
            "светлый",
            "блюдо",
            "свобода",
            "слабый",
            "добрый",
            "слабее",
            "особый",
            "готов",
            "проход",
            "содовая",
            "стоял",
            "бодрый",
            "соболь",
            "любимый",
            "годовой",
            "робкий"
        ]
    },
    {
        "word_id":481304,
        "word":"вольнолюбивый",
        "ref_id":1,
        "setting_id":2,
        "simlar_words":[
            "больше",
            "вблизи",
            "должен",
            "готовый",
            "письмо",
            "полный",
            "великолепный",
            "красноречивый",
            "позже",
            "новый",
            "особый",
            "лосины",
            "готов",
            "больно",
            "брюки",
            "честолюбивый",
            "грешный",
            "уборщик",
            "ленивый",
            "восприимчивый",
            "голос"
        ]
    },
    {
        "word_id":481328,
        "word":"отсрочки",
        "ref_id":1,
        "setting_id":1,
        "simlar_words":[
            "отставка",
            "выкройка",
            "оболочка",
            "отрыжка",
            "тапочки",
            "девочка",
            "коробка",
            "дорожка",
            "отбросы",
            "тарелка",
            "пустота",
            "открытка",
            "сторона",
            "тумбочка",
            "отговорка",
            "обработка",
            "готовка",
            "староста",
            "обертка",
            "красотка"
        ]
    },
    {
        "word_id":481328,
        "word":"отсрочек",
        "ref_id":1,
        "setting_id":2,
        "simlar_words":[
            "отставка",
            "выкройка",
            "ресничка",
            "оболочка",
            "десяток",
            "отрыжка",
            "тапочки",
            "девочка",
            "дорожка",
            "толстовка",
            "папочка",
            "кофемолка",
            "истерика",
            "отбросы",
            "тарелка",
            "открытка",
            "сторона",
            "тумбочка",
            "готовка",
            "отвёртка",
            "обертка"
        ]
    },
    {
        "word_id":481361,
        "word":"розовощекий",
        "ref_id":1,
        "setting_id":1,
        "simlar_words":[
            "молодожены",
            "овчарка",
            "хорошенький",
            "руководство",
            "разнорабочий",
            "творческий",
            "подходящий",
            "запасы",
            "исполинский",
            "разговорно",
            "полнощекий",
            "осень",
            "вопрос",
            "конический",
            "разговорный",
            "около",
            "ползать",
            "пророк",
            "королевский",
            "рыдание",
            "живот",
            "рукопожатие"
        ]
    },
    {
        "word_id":481379,
        "word":"грыжи",
        "ref_id":1,
        "setting_id":1,
        "simlar_words":[
            "хромой",
            "тряпка",
            "роса",
            "гроза",
            "лыжи",
            "кража",
            "гром",
            "губа",
            "река",
            "груша",
            "рыжий",
            "крыша",
            "грива",
            "дыры",
            "лужа",
            "рыба",
            " рот",
            "кожа",
            "слюна",
            "доза",
            "крыса",
            "груши"
        ]
    },
    {
        "word_id":481390,
        "word":"торпедообразное",
        "ref_id":1,
        "setting_id":1,
        "simlar_words":[
            "трудный",
            "должен",
            "грязный",
            "опасный",
            "случай",
            "разный",
            "печеный",
            "добрый",
            "топор",
            "точный",
            "среда",
            "удивлен",
            "обитать",
            "нежный",
            "вредный",
            "трезвый",
            "образ",
            "удобный",
            "труднее",
            "лапша",
            "тупой"
        ]
    },
    {
        "word_id":481392,
        "word":"чернорабочего",
        "ref_id":1,
        "setting_id":1,
        "simlar_words":[
            "экран",
            "сериал",
            "ненормальный",
            "разнорабочий",
            "безошибочный",
            "гений",
            "верно",
            "броги",
            "через",
            "чернила",
            "строго",
            "упрямый",
            "зерно",
            "верный",
            "честолюбивый",
            "общий",
            "лучше",
            "хороший",
            "беспорядочный",
            "робкий"
        ]
    },
    {
        "word_id":481411,
        "word":"зять",
        "ref_id":1,
        "setting_id":1,
        "simlar_words":[
            "лист",
            "чем",
            "отдел",
            "зуб",
            "метка",
            "яма",
            "нить",
            "зад",
            "мяч",
            "акт",
            "пот",
            "связь",
            "кот",
            "мимо",
            "сто",
            "сеть",
            "мать",
            "путь",
            "тех",
            "ряд",
            "бязь",
            "июнь"
        ]
    },
    {
        "word_id":481443,
        "word":"никосия",
        "ref_id":1,
        "setting_id":1,
        "simlar_words":[
            "буксир",
            "низший",
            "бикини",
            "видение",
            "анимация",
            "ирония",
            "калория",
            "философ",
            "лучший",
            "косить",
            "широкий",
            "никогда",
            "лекция",
            "трикотаж",
            "некогда",
            "носить",
            "низкий",
            "эмоции",
            "наконец",
            "мелодия"
        ]
    },
    {
        "word_id":481443,
        "word":"Никосия",
        "ref_id":1,
        "setting_id":3,
        "simlar_words":[
            "никуда",
            "секция",
            "калория",
            "ирония",
            "история",
            "философ",
            "косить",
            "нутрия",
            "широкий",
            "никогда",
            "новости",
            "лекция",
            "некогда",
            "носить",
            "низкий",
            "эмоции",
            "пенсия",
            "наконец",
            "жидкость",
            "мелодия"
        ]
    },
    {
        "word_id":481463,
        "word":"несотрудничающих",
        "ref_id":1,
        "setting_id":1,
        "simlar_words":[
            "унижать",
            "судить",
            "стихать",
            "стричь",
            "кричал",
            "кричать",
            "неудача",
            "кричит",
            "держал",
            "стучать",
            "нестись",
            "струна",
            "понимая",
            "создал",
            "неволя",
            "настораживающий",
            "обучать",
            "находит",
            "петли",
            "стирать",
            "снимать"
        ]
    },
    {
        "word_id":481465,
        "word":"Краков",
        "ref_id":1,
        "setting_id":1,
        "simlar_words":[
            "кровь",
            "какао",
            "кража",
            "крепкий",
            "мрамор",
            "дракон",
            "закон",
            "крючки",
            "совок",
            "слабее",
            "крючок",
            "зрачок",
            "красота",
            "скрытый",
            "кузов",
            "травма",
            "рукав",
            "капот",
            "право",
            "рукава",
            "крыса",
            "крылья"
        ]
    },
    {
        "word_id":481469,
        "word":"фюзеляжи",
        "ref_id":1,
        "setting_id":1,
        "simlar_words":[
            "стрелять",
            "разделять",
            "кремний",
            "поцелуй",
            "пылесос",
            "слизерин",
            "кошелёк",
            "позволять",
            "времена",
            "веселье",
            "розетка",
            "синяк",
            "избегать",
            "тарелка",
            "мудрее",
            "молоток",
            "незрелый",
            "ударяющий",
            "любезно",
            "разделяет",
            "перелом",
            "исцелять"
        ]
    },
    {
        "word_id":481469,
        "word":"фюзеляжей",
        "ref_id":1,
        "setting_id":2,
        "simlar_words":[
            "стрелять",
            "разделять",
            "зонтик",
            "доверять",
            "драма",
            "хамелеон",
            "слизерин",
            "величайший",
            "изменять",
            "удивлять",
            "веселье",
            "дельфин",
            "владелец",
            "загорелый",
            "перевязь",
            "ладить",
            "любезный",
            "незрелый",
            "отказ",
            "разделяет",
            "чудесный",
            "исцелять"
        ]
    },
    {
        "word_id":481533,
        "word":"треска",
        "ref_id":1,
        "setting_id":1,
        "simlar_words":[
            "трусы",
            "стейк",
            "кресло",
            "ярлык",
            "стрелы",
            "грехи",
            "отпуск",
            "время",
            "юрист",
            "времена",
            "трусики",
            "стрела",
            "бремя",
            "гренки",
            "среда",
            "поиски",
            "крест",
            "траур",
            "труба",
            "блеск"
        ]
    },
    {
        "word_id":481563,
        "word":"ласточки",
        "ref_id":1,
        "setting_id":1,
        "simlar_words":[
            "отставка",
            "ресничка",
            "тапочки",
            "девочка",
            "частично",
            "папочка",
            "кавычка",
            "частота",
            "частица",
            "насмешки",
            "катушка",
            "пустота",
            "лестница",
            "мартышка",
            "важность",
            "кастрюля",
            "вспышка",
            "готовка",
            "бастовать",
            "расточать",
            "лампочка"
        ]
    },
    {
        "word_id":481563,
        "word":"Ласточкино",
        "ref_id":1,
        "setting_id":2,
        "simlar_words":[
            "логово",
            "крестьянин",
            "раскопанный",
            "восточный",
            "настойчивый",
            "расстояние",
            "настойчиво",
            "блестящий",
            "викторина",
            "наставник",
            "посещение",
            "состояние",
            "чертовски",
            "счета",
            "настроение",
            "бастовать",
            "уборщик",
            "настроения",
            "настоящий",
            "расточать"
        ]
    },
    {
        "word_id":481609,
        "word":"непрерывно",
        "ref_id":1,
        "setting_id":1,
        "simlar_words":[
            "рендеринг",
            "проза",
            "ежедневно",
            "прерывающий",
            "горло",
            "нигде",
            "запрещать",
            "крыльцо",
            "невероятно",
            "ремесло",
            "прерывать",
            "фитнес",
            "непременно",
            "немедленно",
            "невеста",
            "жеребёнок",
            "терпеливо",
            "неприятие",
            "направление",
            "скорее",
            "рукава",
            "непрерывный"
        ]
    },
    {
        "word_id":481609,
        "word":"постоянно",
        "ref_id":1,
        "setting_id":2,
        "simlar_words":[
            "постепенно",
            "проснуться",
            "отчаянно",
            "восточный",
            "потерянный",
            "достойный",
            "постоянный",
            "поспешно",
            "цветок",
            "осторожно",
            "ответ",
            "состояние",
            "допущение",
            "просторный",
            "особенно",
            "помощник",
            "основной",
            "мотоцикл",
            "собственно",
            "поставщик",
            "состоять",
            "смущать"
        ]
    },
    {
        "word_id":481627,
        "word":"полуквартале",
        "ref_id":1,
        "setting_id":1,
        "simlar_words":[
            "переваривать",
            "произрастать",
            "послезавтра",
            "волноваться",
            "подавленный",
            "посвящённый",
            "пользоваться",
            "рвать",
            "карьера",
            "последователь",
            "подобранный",
            "потребитель",
            "пищеварение",
            "полупансион",
            "пытать",
            "кобра",
            "отвергаемый",
            "процветающий",
            "подтверждать",
            "сатин",
            "подвластный",
            "подавляющий"
        ]
    },
    {
        "word_id":481667,
        "word":"соразмерен",
        "ref_id":1,
        "setting_id":2,
        "simlar_words":[
            "возможный",
            "крошечный",
            "свежий",
            "надменный",
            "солнечный",
            "собранный",
            "совместный",
            "беременная",
            "сердечный",
            "различный",
            "сырой",
            "чрезмерно",
            "чрезмерный",
            "обычный",
            "формальный",
            "бесполезный",
            "переменная",
            "неизменный",
            "свадебный",
            "прачечная",
            "гламурный",
            "современный"
        ]
    },
    {
        "word_id":481677,
        "word":"спиричуэлс",
        "ref_id":1,
        "setting_id":4,
        "simlar_words":[
            "служитель",
            "причудливый",
            "единичный",
            "скрипучий",
            "спортивный",
            "спортсмен",
            "впихивать",
            "спрятанный",
            "покинутый",
            "первичный",
            "истеричный",
            "порошок",
            "груши",
            "сливочный",
            "перечница",
            "споткнулся",
            "справиться",
            "специалист",
            "причинять",
            "придумали",
            "другие"
        ]
    },
    {
        "word_id":481679,
        "word":"шотландка",
        "ref_id":1,
        "setting_id":1,
        "simlar_words":[
            "голубика",
            "приманка",
            "ирландцы",
            "маслёнка",
            "оплаченный",
            "больница",
            "лихорадка",
            "полукровка",
            "заплатка",
            "растрата",
            "водолазка",
            "страница",
            "согласие",
            "открытка",
            "поясница",
            "отвёртка",
            "политика",
            "подкладка",
            "совпадать",
            "остановка",
            "доставка"
        ]
    },
    {
        "word_id":481697,
        "word":"италии",
        "ref_id":1,
        "setting_id":1,
        "simlar_words":[
            "тарифы",
            "статья",
            "чиханье",
            "авария",
            "злоба",
            "ирония",
            "апатия",
            "тащить",
            "желание",
            "стадия",
            "барибал",
            "талия",
            "мании",
            "питание",
            "гасить",
            "мания",
            "сталь",
            "инвалид",
            "малина",
            "вдаль",
            "знать",
            "чинить"
        ]
    },
    {
        "word_id":481707,
        "word":"полностью",
        "ref_id":1,
        "setting_id":2,
        "simlar_words":[
            "понимать",
            "завлекать",
            "плотность",
            "относиться",
            "гордость",
            "получать",
            "упомянутый",
            "потливость",
            "приносить",
            "сложность",
            "прочность",
            "сущность",
            "жадность",
            "молодость",
            "беспокоить",
            "толковать",
            "подростки",
            "полагать",
            "положить",
            "опасность"
        ]
    },
    {
        "word_id":481722,
        "word":"сюжетом",
        "ref_id":1,
        "setting_id":1,
        "simlar_words":[
            "любить",
            "сбежать",
            "брюнет",
            "паштет",
            "сожалеть",
            "скелет",
            "спасать",
            "бюджет",
            "тяжело",
            "акцент",
            "студент",
            "соседи",
            "десерт",
            "лежащий",
            "диабет",
            "сияющий",
            "падать",
            "хотеть",
            "летающий",
            "лежать",
            "монеты",
            "гореть"
        ]
    },
    {
        "word_id":481729,
        "word":"многоуровневые",
        "ref_id":1,
        "setting_id":1,
        "simlar_words":[
            "многосторонний",
            "много",
            "умный",
            "нервный",
            "хриплый",
            "ранен",
            "жирный",
            "многочисленный",
            "ровный",
            "готовый",
            "бронх",
            "вкусный",
            "новый",
            "уровень",
            "готов",
            "мокрый",
            "суровый",
            "муравей",
            "немногословный",
            "сонный"
        ]
    },
    {
        "word_id":481729,
        "word":"многоуровневый",
        "ref_id":1,
        "setting_id":2,
        "simlar_words":[
            "многосторонний",
            "много",
            "умный",
            "нервный",
            "ранен",
            "грязный",
            "многочисленный",
            "ровный",
            "готовый",
            "моющий",
            "должный",
            "новый",
            "уровень",
            "насилие",
            "готов",
            "охотно",
            "буфет",
            "суровый",
            "муравей",
            "грубый",
            "лучше",
            "немногословный"
        ]
    },
    {
        "word_id":481748,
        "word":"гаррус",
        "ref_id":1,
        "setting_id":1,
        "simlar_words":[
            "глупый",
            "русый",
            "гордый",
            "тугой",
            "старый",
            "грязный",
            "научный",
            "вареный",
            "украл",
            "глупец",
            "газон",
            "жареный",
            "герой",
            "местный",
            "грешный",
            "всякий",
            "удобный",
            "грубый",
            "перелом",
            "грусть"
        ]
    },
    {
        "word_id":481777,
        "word":"петербург",
        "ref_id":1,
        "setting_id":1,
        "simlar_words":[
            "побережье",
            "литература",
            "ветреный",
            "переулок",
            "сентябрь",
            "ветеринар",
            "дементор",
            "неверный",
            "пятиборье",
            "лекарство",
            "менеджер",
            "фейерверк",
            "нетронутый",
            "нотариус",
            "переговоры",
            "невестка",
            "северный",
            "перечница",
            "перевязь",
            "пересказ",
            "пережить",
            "метеоролог"
        ]
    },
    {
        "word_id":481779,
        "word":"филиал",
        "ref_id":1,
        "setting_id":2,
        "simlar_words":[
            "фитиль",
            "бикини",
            "сериал",
            "белок",
            "ритуал",
            "зеркало",
            "барибал",
            "фигня",
            "портал",
            "шакал",
            "чёлка",
            "вилка",
            "скала",
            "жилье",
            "билет",
            "клиент",
            "сигналы",
            "слива",
            "палка",
            "кинжал",
            "почва",
            "фраза"
        ]
    },
    {
        "word_id":481790,
        "word":"сохранённый",
        "ref_id":1,
        "setting_id":2,
        "simlar_words":[
            "поражённый",
            "подавленный",
            "окруженный",
            "производить",
            "оплаченный",
            "пораженный",
            "похоронить",
            "утраченный",
            "прекратить",
            "совершённый",
            "соблазнять",
            "искривлённый",
            "захваченный",
            "доставленный",
            "запрещённый",
            "погруженный",
            "соединённый",
            "воспалённый",
            "схватывать",
            "приглушенный",
            "испуганный",
            "озабоченный"
        ]
    },
    {
        "word_id":481790,
        "word":"цфат",
        "ref_id":1,
        "setting_id":3,
        "simlar_words":[
            "закат",
            "плата",
            "себя",
            "перья",
            "фен",
            "рак",
            "кит",
            "бунт",
            "брат",
            "куст",
            "суд",
            "факт",
            "храм",
            "таз",
            "цирк",
            "май",
            "кот",
            "дар",
            "опыт",
            "омар",
            "зал",
            "щит"
        ]
    },
    {
        "word_id":481812,
        "word":"операционная",
        "ref_id":1,
        "setting_id":1,
        "simlar_words":[
            "безработный",
            "неграмотный",
            "определённый",
            "непреклонный",
            "опека",
            "заграничный",
            "ограниченный",
            "традиционный",
            "равноценный",
            "отверженный",
            "откровенный",
            "непостоянный",
            "равный",
            "неправильный",
            "грандиозный",
            "совершенный",
            "впечатленный",
            "описательный",
            "поразительный",
            "религиозный",
            "ненавистный",
            "длинный"
        ]
    },
    {
        "word_id":481822,
        "word":"нейлор",
        "ref_id":1,
        "setting_id":1,
        "simlar_words":[
            "седло",
            "небеса",
            "белка",
            "налог",
            "ужасно",
            "рефери",
            "трейлер",
            "после",
            "поток",
            "номер",
            "нейлон",
            "собор",
            "земля",
            "налоги",
            "место",
            "войлок",
            "ребро",
            "зерно",
            "мешок",
            "хищники",
            "чулок",
            "неясный"
        ]
    },
    {
        "word_id":481825,
        "word":"сстг",
        "ref_id":1,
        "setting_id":1,
        "simlar_words":[
            "много",
            "луг",
            "седой",
            "вне",
            "бег",
            "кит",
            "вонь",
            "суд",
            "сито",
            "сено",
            "снег",
            "сын",
            "уста",
            "шаг",
            "усы",
            "кот",
            "сто",
            "сеть",
            "слог",
            "соя",
            "сыр"
        ]
    },
    {
        "word_id":481826,
        "word":"цкт",
        "ref_id":1,
        "setting_id":4,
        "simlar_words":[
            "нет",
            "ещё",
            "кит",
            "лук",
            "факт",
            "дно",
            "там",
            "акт",
            "кого",
            "пот",
            "над",
            "тоже",
            "тут",
            "кот",
            "кто",
            "тех",
            "ушел",
            "вот",
            "цикл",
            "дух"
        ]
    },
    {
        "word_id":481834,
        "word":"сгибать",
        "ref_id":1,
        "setting_id":3,
        "simlar_words":[
            "свисать",
            "стихать",
            "кидать",
            "исчезать",
            "сжимать",
            "читать",
            "вешать",
            "ошибка",
            "считать",
            "погибать",
            "сосать",
            "обитать",
            "писать",
            "сбивать",
            "сидеть",
            "тратить",
            "хватать",
            "играть",
            "пинать",
            "стирать",
            "снимать",
            "порицать"
        ]
    },
    {
        "word_id":481834,
        "word":"бенг",
        "ref_id":1,
        "setting_id":5,
        "simlar_words":[
            "лень",
            "бог",
            "тост",
            "цена",
            "день",
            "вне",
            "бег",
            "врозь",
            "фен",
            "меню",
            "усы",
            "мой",
            "берег",
            "вена",
            "свеча",
            "дуть",
            "жена",
            "обед",
            "белье",
            "музей",
            "ночь",
            "бок"
        ]
    },
    {
        "word_id":481853,
        "word":"лундберг",
        "ref_id":1,
        "setting_id":1,
        "simlar_words":[
            "рендеринг",
            "блендер",
            "бунтарь",
            "ондатра",
            "кондитер",
            "введение",
            "ленивец",
            "менеджер",
            "четверг",
            "пантера",
            "сноуборд",
            "бухгалтер",
            "пуловер",
            "мольберт",
            "конверт",
            "фундамент",
            "концерт",
            "удобный",
            "лицемерие",
            "поперёк",
            "универмаг"
        ]
    },
    {
        "word_id":481885,
        "word":"МЭК",
        "ref_id":1,
        "setting_id":3,
        "simlar_words":[
            "вид",
            "мрак",
            "муж",
            "мало",
            "рак",
            "море",
            "друг",
            "сок",
            "как",
            "без",
            "нам",
            "чек",
            "кот",
            "зло",
            "моё",
            "мир",
            "мука",
            "меч",
            "бык",
            "маяк",
            "бок"
        ]
    },
    {
        "word_id":481898,
        "word":"олы",
        "ref_id":1,
        "setting_id":3,
        "simlar_words":[
            "увы",
            "пока",
            "для",
            "зола",
            "волк",
            "коза",
            "они",
            "оба",
            "воля",
            "ноль",
            "гол",
            "клык",
            "его",
            "нам",
            "оно",
            "зло",
            "вол",
            "боль",
            "опыт",
            "доля",
            "она"
        ]
    },
    {
        "word_id":481898,
        "word":"мнк",
        "ref_id":1,
        "setting_id":4,
        "simlar_words":[
            "мрак",
            "вне",
            "муж",
            "рак",
            "внук",
            "море",
            "меню",
            "сок",
            "оба",
            "дно",
            "умно",
            "поле",
            "его",
            "нам",
            "банк",
            "мёд",
            "знак",
            "мир",
            "ему",
            "мука",
            "маяк"
        ]
    },
    {
        "word_id":481918,
        "word":"якоби",
        "ref_id":1,
        "setting_id":1,
        "simlar_words":[
            "корь",
            "хотя",
            "злоба",
            "школа",
            "коза",
            "киви",
            "лобби",
            "кофе",
            "гроб",
            "колли",
            "якорь",
            "скобка",
            "бобы",
            "кобра",
            "бобр",
            "корт",
            "пробы",
            "кожа",
            "укол",
            "актив",
            "скорее"
        ]
    },
    {
        "word_id":481923,
        "word":"вакцинация",
        "ref_id":1,
        "setting_id":1,
        "simlar_words":[
            "мотивация",
            "начинания",
            "временами",
            "антипатия",
            "облигация",
            "вымирание",
            "декорации",
            "кульминация",
            "навигация",
            "реализация",
            "напоминает",
            "аннотация",
            "медитация",
            "наклоняться",
            "упоминать",
            "выживание",
            "информация",
            "квитанция",
            "аллитерация",
            "заклинание"
        ]
    },
    {
        "word_id":481923,
        "word":"иммунизация",
        "ref_id":1,
        "setting_id":2,
        "simlar_words":[
            "бунтарь",
            "инструкция",
            "иногда",
            "рифма",
            "унция",
            "хитрый",
            "коннотация",
            "махание",
            "вкусный",
            "кульминация",
            "ребята",
            "реализация",
            "концентрация",
            "ерунда",
            "кость",
            "страх",
            "информация",
            "монография",
            "экранизация",
            "амортизатор",
            "рыдание",
            "трансляция"
        ]
    },
    {
        "word_id":481923,
        "word":"прививки",
        "ref_id":1,
        "setting_id":3,
        "simlar_words":[
            "привычки",
            "причины",
            "причина",
            "критика",
            "приманка",
            "провидец",
            "плащевка",
            "мировой",
            "инсульт",
            "солонка",
            "прибыль",
            "проволока",
            "прищепка",
            "приходить",
            "ожидание",
            "проповедь",
            "привычка",
            "проверка",
            "блюдце",
            "общий",
            "простыня",
            "причинять"
        ]
    },
    {
        "word_id":481940,
        "word":"саморегулироваться",
        "ref_id":1,
        "setting_id":1,
        "simlar_words":[
            "моргать",
            "удалось",
            "поливая",
            "срывать",
            "сделал",
            "скулить",
            "зарегистрироваться",
            "смерть",
            "словари",
            "считать",
            "сломал",
            "сгибать",
            "морковь",
            "неволя",
            "требует",
            "смущён",
            "молоть",
            "учиться",
            "мчаться",
            "петли",
            "стирать"
        ]
    },
    {
        "word_id":481953,
        "word":"малого",
        "ref_id":1,
        "setting_id":1,
        "simlar_words":[
            "палки",
            "налог",
            "майонез",
            "закон",
            "талия",
            "галерея",
            "мания",
            "малыш",
            "масло",
            "маска",
            "налоги",
            "каток",
            "марка",
            "малина",
            "голод",
            "мешок",
            "холод",
            "легкое",
            "залог",
            "палка",
            "диалог",
            "жалоба"
        ]
    },
    {
        "word_id":481953,
        "word":"мелкомасштабный",
        "ref_id":1,
        "setting_id":2,
        "simlar_words":[
            "плотно",
            "кожаный",
            "штаны",
            "сказать",
            "опасный",
            "красный",
            "способ",
            "лысый",
            "должный",
            "особый",
            "масштаб",
            "лосины",
            "обитать",
            "честный",
            "местный",
            "милый",
            "частный",
            "пышный",
            "общий",
            "легкомысленный"
        ]
    },
    {
        "word_id":481959,
        "word":"дошкольное",
        "ref_id":1,
        "setting_id":1,
        "simlar_words":[
            "нормальный",
            "упитанный",
            "ближний",
            "ранний",
            "достаточный",
            "достойный",
            "далеко",
            "довольный",
            "бесконечный",
            "прекрасный",
            "отдельный",
            "формальный",
            "недовольный",
            "социальный",
            "роскошный",
            "тщательный",
            "решительный",
            "доступный",
            "миловидный",
            "лучше",
            "понос",
            "горький"
        ]
    },
    {
        "word_id":481973,
        "word":"сян",
        "ref_id":1,
        "setting_id":2,
        "simlar_words":[
            "стон",
            "сова",
            "яма",
            "суд",
            "суп",
            "сено",
            "сын",
            "пас",
            "сани",
            "его",
            "еще",
            "есть",
            "сны",
            "сон",
            "няня",
            "слон",
            "ему",
            "ряд",
            "меня",
            "сыр"
        ]
    }
]