{
    "head": {},
    "def": [
        {
            "text": "flatulent",
            "pos": "adjective",
            "ts": "ˈflætjʊlənt",
            "tr": [
                {
                    "text": "претенциозный",
                    "pos": "adjective",
                    "syn": [
                        {
                            "text": "напыщенный",
                            "pos": "adjective"
                        }
                    ],
                    "mean": [
                        {
                            "text": "pretentious"
                        },
                        {
                            "text": "pompous"
                        }
                    ]
                }
            ]
        }
    ]
}