{
    "head": {},
    "def": [
        {
            "text": "innovation",
            "pos": "noun",
            "ts": "ɪnəˈveɪʃn",
            "tr": [
                {
                    "text": "инновация",
                    "pos": "noun",
                    "gen": "ж",
                    "syn": [
                        {
                            "text": "нововведение",
                            "pos": "noun",
                            "gen": "ср"
                        },
                        {
                            "text": "новшество",
                            "pos": "noun",
                            "gen": "ср"
                        },
                        {
                            "text": "новаторство",
                            "pos": "noun",
                            "gen": "ср"
                        },
                        {
                            "text": "новация",
                            "pos": "noun",
                            "gen": "ж"
                        },
                        {
                            "text": "новинка",
                            "pos": "noun",
                            "gen": "ж"
                        },
                        {
                            "text": "инновационная деятельность",
                            "pos": "noun"
                        },
                        {
                            "text": "новизна",
                            "pos": "noun",
                            "gen": "ж"
                        },
                        {
                            "text": "новаторская деятельность",
                            "pos": "noun"
                        }
                    ],
                    "mean": [
                        {
                            "text": "innovate"
                        },
                        {
                            "text": "novelty"
                        },
                        {
                            "text": "innovative"
                        },
                        {
                            "text": "novation"
                        },
                        {
                            "text": "innovative activity"
                        }
                    ],
                    "ex": [
                        {
                            "text": "centre for social innovation",
                            "tr": [
                                {
                                    "text": "центр социальных инноваций"
                                }
                            ]
                        },
                        {
                            "text": "technological innovation",
                            "tr": [
                                {
                                    "text": "технологическое нововведение"
                                }
                            ]
                        },
                        {
                            "text": "number of technical innovations",
                            "tr": [
                                {
                                    "text": "ряд технических новшеств"
                                }
                            ]
                        },
                        {
                            "text": "true innovation",
                            "tr": [
                                {
                                    "text": "истинное новаторство"
                                }
                            ]
                        },
                        {
                            "text": "radical innovation",
                            "tr": [
                                {
                                    "text": "радикальная новация"
                                }
                            ]
                        },
                        {
                            "text": "next innovation",
                            "tr": [
                                {
                                    "text": "очередная новинка"
                                }
                            ]
                        },
                        {
                            "text": "scientific innovation",
                            "tr": [
                                {
                                    "text": "научная новизна"
                                }
                            ]
                        }
                    ]
                },
                {
                    "text": "рационализаторство",
                    "pos": "noun",
                    "gen": "ср",
                    "mean": [
                        {
                            "text": "rationalization"
                        }
                    ]
                },
                {
                    "text": "внедрение инноваций",
                    "pos": "noun",
                    "syn": [
                        {
                            "text": "внедрение новшеств",
                            "pos": "noun"
                        }
                    ],
                    "mean": [
                        {
                            "text": "introduction of innovations"
                        }
                    ]
                },
                {
                    "text": "инновационность",
                    "pos": "noun",
                    "gen": "ж"
                },
                {
                    "text": "изобретение",
                    "pos": "noun",
                    "gen": "ср",
                    "mean": [
                        {
                            "text": "invention"
                        }
                    ],
                    "ex": [
                        {
                            "text": "new innovations",
                            "tr": [
                                {
                                    "text": "новые изобретения"
                                }
                            ]
                        }
                    ]
                },
                {
                    "text": "обновление",
                    "pos": "noun",
                    "gen": "ср",
                    "mean": [
                        {
                            "text": "update"
                        }
                    ]
                },
                {
                    "text": "Новелла",
                    "pos": "noun",
                    "gen": "ж"
                },
                {
                    "text": "рационализаторское предложение",
                    "pos": "noun",
                    "mean": [
                        {
                            "text": "rationalization proposal"
                        }
                    ]
                }
            ]
        },
        {
            "text": "innovation",
            "pos": "adjective",
            "ts": "ɪnəˈveɪʃn",
            "tr": [
                {
                    "text": "инновационный",
                    "pos": "adjective",
                    "syn": [
                        {
                            "text": "внедренческий",
                            "pos": "adjective"
                        }
                    ],
                    "mean": [
                        {
                            "text": "innovative"
                        },
                        {
                            "text": "promotional"
                        }
                    ],
                    "ex": [
                        {
                            "text": "innovation project",
                            "tr": [
                                {
                                    "text": "инновационный проект"
                                }
                            ]
                        },
                        {
                            "text": "development of innovation technologies",
                            "tr": [
                                {
                                    "text": "развитие инновационных технологий"
                                }
                            ]
                        },
                        {
                            "text": "innovation activity of enterprises",
                            "tr": [
                                {
                                    "text": "инновационная деятельность предприятий"
                                }
                            ]
                        },
                        {
                            "text": "national system of innovation",
                            "tr": [
                                {
                                    "text": "национальная инновационная система"
                                }
                            ]
                        }
                    ]
                }
            ]
        }
    ]
}