{
    "head": {},
    "def": [
        {
            "text": "Mujahideen",
            "pos": "noun",
            "ts": "muːʤɪhedˈiːn",
            "tr": [
                {
                    "text": "моджахеды",
                    "pos": "noun",
                    "gen": "м",
                    "mean": [
                        {
                            "text": "mujahedeen"
                        }
                    ]
                },
                {
                    "text": "муджахиды",
                    "pos": "noun",
                    "gen": "м"
                }
            ]
        }
    ]
}