{
    "head": {},
    "def": [
        {
            "text": "solemnity",
            "pos": "noun",
            "ts": "səˈlemnɪtɪ",
            "tr": [
                {
                    "text": "серьезность",
                    "pos": "noun",
                    "gen": "ж",
                    "syn": [
                        {
                            "text": "значимость",
                            "pos": "noun",
                            "gen": "ж"
                        },
                        {
                            "text": "важность",
                            "pos": "noun",
                            "gen": "ж"
                        }
                    ],
                    "mean": [
                        {
                            "text": "seriousness"
                        },
                        {
                            "text": "importance"
                        }
                    ]
                },
                {
                    "text": "торжественность",
                    "pos": "noun",
                    "gen": "ж",
                    "syn": [
                        {
                            "text": "импозантность",
                            "pos": "noun",
                            "gen": "ж"
                        }
                    ],
                    "mean": [
                        {
                            "text": "gravity"
                        }
                    ]
                },
                {
                    "text": "торжество",
                    "pos": "noun",
                    "gen": "ср",
                    "mean": [
                        {
                            "text": "celebration"
                        }
                    ]
                },
                {
                    "text": "торжественная церемония",
                    "pos": "noun",
                    "mean": [
                        {
                            "text": "solemn ceremony"
                        }
                    ]
                }
            ]
        }
    ]
}